bitcrawl/__init__.py
bitcrawl/cli.py
bitcrawl/contextual_searcher.py
bitcrawl/core.py
bitcrawl/internal_crawler.py
bitcrawl-0.0.1.dist-info/LICENSE
bitcrawl-0.0.1.dist-info/METADATA
bitcrawl-0.0.1.dist-info/WHEEL
bitcrawl-0.0.1.dist-info/entry_points.txt
bitcrawl-0.0.1.dist-info/top_level.txt
bitcrawl-0.0.1.dist-info/RECORD
